LICENSE
MANIFEST.in
README.md
requirements.txt
setup.py
melkit/__init__.py
melkit/_ptf.py
melkit/constants.py
melkit/exceptions.py
melkit/inputs.py
melkit/toolkit.py
melkit/version.txt
melkit.egg-info/PKG-INFO
melkit.egg-info/SOURCES.txt
melkit.egg-info/dependency_links.txt
melkit.egg-info/requires.txt
melkit.egg-info/top_level.txt