Metadata-Version: 2.1
Name: melkit
Version: 0.4
Summary: A toolkit designed to facilitate the handling of MELCOR/MELGEN 1.8.6 files.
Home-page: https://github.com/manjavacas/melkit
Author: Antonio Manjavacas
Author-email: manjavacas@ugr.es
License: GPL3
Keywords: toolkit,melcor,melcor-fusion,melgen
Platform: UNKNOWN
Provides-Extra: doc
License-File: LICENSE
